{"cameraMode":{"drawMode":0,"name":"Shaded","section":"Shading Mode"},"sceneLighting":true,"audioPlay":false,"sceneViewState":{"m_AlwaysRefresh":false,"showFog":true,"showSkybox":true,"showFlares":true,"showImageEffects":true,"showParticleSystems":true,"showVisualEffectGraphs":true,"m_FxEnabled":true},"in2DMode":false,"pivot":{"x":38.39591979980469,"y":-3.5686745643615724,"z":75.75774383544922},"rotation":{"x":-0.10665624588727951,"y":-0.7956308126449585,"z":0.1471261978149414,"w":-0.5781071782112122},"size":1.2729861736297608,"orthographic":false}